aiida_tools/__init__.py
aiida_tools/_check_workchain_step.py
aiida_tools/_get_outputs_dict.py
aiida_tools/process_inputs.py
aiida_tools-0.4.1.dist-info/LICENSE.txt
aiida_tools-0.4.1.dist-info/METADATA
aiida_tools-0.4.1.dist-info/WHEEL
aiida_tools-0.4.1.dist-info/top_level.txt
aiida_tools-0.4.1.dist-info/RECORD
